[
  {
    "kind": "joke",
    "title": "Le livre froid",
    "body": "Pourquoi le livre est-il alle au frigo ? Parce qu'il voulait lire une histoire bien fraiche avant le petit-dejeuner."
  },
  {
    "kind": "joke",
    "title": "La tartine",
    "body": "Que dit la tartine grillee quand elle est tres contente ? Je suis crousti-formidable aujourd'hui."
  },
  {
    "kind": "joke",
    "title": "Le nuage",
    "body": "Pourquoi le petit nuage emporte-t-il un parapluie ? Parce qu'il ne veut pas se faire arroser par surprise."
  },
  {
    "kind": "joke",
    "title": "Le crayon",
    "body": "Que dit le crayon avant une grande dictee ? Je suis pret, j'ai deja bien taille mon courage."
  },
  {
    "kind": "joke",
    "title": "Le lapin",
    "body": "Pourquoi le lapin raconte-t-il des blagues au jardin ? Parce qu'il adore faire rire les carottes."
  },
  {
    "kind": "joke",
    "title": "Le reveil",
    "body": "Pourquoi le reveil est-il si fier le matin ? Parce qu'il reussit toujours son entree a l'heure."
  },
  {
    "kind": "joke",
    "title": "Le cartable",
    "body": "Que dit le cartable quand il est trop plein ? Ouh la, aujourd'hui j'ai avale toute la classe."
  },
  {
    "kind": "joke",
    "title": "Le biscuit",
    "body": "Pourquoi le biscuit va-t-il a l'ecole ? Pour devenir un vrai petit genie croustillant."
  }
]
